./.gitignore
./LICENSE
./PKG-INFO
./README.md
./main.py
./pyproject.toml
./scraper.py
./test_mcp_server.py
./uv.lock
huggingface_daily_paper_mcp-0.1.4.dist-info/METADATA
huggingface_daily_paper_mcp-0.1.4.dist-info/WHEEL
huggingface_daily_paper_mcp-0.1.4.dist-info/entry_points.txt
huggingface_daily_paper_mcp-0.1.4.dist-info/licenses/LICENSE
huggingface_daily_paper_mcp-0.1.4.dist-info/RECORD
