Metadata-Version: 2.4
Name: huggingface-daily-paper-mcp
Version: 0.1.4
Summary: A MCP server for fetching HuggingFace daily papers
Project-URL: Homepage, https://github.com/huangxinping/huggingface-daily-paper-mcp
Project-URL: Repository, https://github.com/huangxinping/huggingface-daily-paper-mcp.git
Project-URL: Issues, https://github.com/huangxinping/huggingface-daily-paper-mcp/issues
Author-email: huangxinping <monor.huang@gmail.com>
License: MIT
License-File: LICENSE
Keywords: ai,huggingface,mcp,papers,server
Classifier: Development Status :: 4 - Beta
Classifier: Intended Audience :: Developers
Classifier: License :: OSI Approved :: MIT License
Classifier: Programming Language :: Python :: 3
Classifier: Programming Language :: Python :: 3.10
Classifier: Programming Language :: Python :: 3.11
Classifier: Programming Language :: Python :: 3.12
Classifier: Topic :: Scientific/Engineering :: Artificial Intelligence
Classifier: Topic :: Software Development :: Libraries :: Python Modules
Requires-Python: >=3.10
Requires-Dist: beautifulsoup4>=4.13.5
Requires-Dist: lxml>=6.0.1
Requires-Dist: mcp>=1.13.1
Requires-Dist: pydantic>=2.0.0
Requires-Dist: requests>=2.32.5
